JsonFlow/__init__.py
JsonFlow/jsonify.py
JsonFlow/main.py
JsonFlow/utils/__init__.py
JsonFlow/utils/parses.py
JsonFlow/utils/samples.py
JsonFlow-0.1.1.2.dist-info/LICENSE
JsonFlow-0.1.1.2.dist-info/METADATA
JsonFlow-0.1.1.2.dist-info/WHEEL
JsonFlow-0.1.1.2.dist-info/top_level.txt
JsonFlow-0.1.1.2.dist-info/RECORD
