Metadata-Version: 2.1
Name: JsonFlow
Version: 0.1.1.2
Author: BecomeAllan
Author-email: becomeallan@gmail.com
License: MIT
Keywords: json,dictionary,manipulation,traversal,nested,extraction,configuration,API,data storage,python,JsonFlow
Classifier: License :: OSI Approved :: MIT License
License-File: LICENSE
Provides-Extra: parse
Requires-Dist: pandoc ; extra == 'parse'
Requires-Dist: beautifulsoup4 ; extra == 'parse'
